MANIFEST.in
README.txt
license.txt
setup.py
Django_Photofile.egg-info/PKG-INFO
Django_Photofile.egg-info/SOURCES.txt
Django_Photofile.egg-info/dependency_links.txt
Django_Photofile.egg-info/not-zip-safe
Django_Photofile.egg-info/requires.txt
Django_Photofile.egg-info/top_level.txt
photofile/__init__.py
photofile/decorators.py
photofile/metadata.py
photofile/models.py
photofile/urls.py
photofile/utils.py
photofile/views.py
photofile/context_processors/__init__.py
photofile/management/__init__.py
photofile/management/commands/__init__.py
photofile/management/commands/relocatephotos.py
photofile/static/css/jquery.lightbox-0.5.css
photofile/static/js/jquery.js
photofile/static/js/jquery.lightbox-0.5.js
photofile/static/js/jquery.lightbox-0.5.min.js
photofile/static/js/jquery.lightbox-0.5.pack.js
photofile/templatetags/__init__.py
photofile/templatetags/photofile_tags.py