Metadata-Version: 1.0
Name: Django-Photofile
Version: 0.5.0
Summary: Templatetags for thumbnail generation, with automatic rotation based on EXIF.Orientation. Among other things.
Home-page: https://bitbucket.org/weholt/django-photofile
Author: Thomas Weholt
Author-email: thomas@weholt.org
License: Modified BSD
Keywords: photo thumbnail generation django metadata
Platform: UNKNOWN
Classifier: Development Status :: 4 - Beta
Classifier: Intended Audience :: Developers
Classifier: Framework :: Django
Classifier: License :: OSI Approved :: BSD License
Classifier: Operating System :: OS Independent
Classifier: Programming Language :: Python
Classifier: Topic :: Database
